django_pint/__init__.py
django_pint-1.0.4.dist-info/licenses/LICENSE.txt
quantityfield/__init__.py
quantityfield/fields.py
quantityfield/helper.py
quantityfield/settings.py
quantityfield/units.py
quantityfield/widgets.py
django_pint-1.0.4.dist-info/METADATA
django_pint-1.0.4.dist-info/WHEEL
django_pint-1.0.4.dist-info/top_level.txt
django_pint-1.0.4.dist-info/RECORD
