Metadata-Version: 2.4
Name: django-pint
Version: 1.0.4
Summary: Quantity Field for Django using pint library for automated unit conversions
Author: Ben Harling
Author-email: Carli* Freudenberg <kound@posteo.de>
Maintainer-email: Carli* Freudenberg <kound@posteo.de>
License-Expression: MIT
Project-URL: Homepage, https://github.com/CarliJoy/django-pint/
Project-URL: Documentation, https://django-pint.readthedocs.io/en/latest/
Project-URL: Source Code, https://github.com/CarliJoy/django-pint/
Project-URL: Bug Tracker, https://github.com/CarliJoy/django-pint/issues
Classifier: Development Status :: 4 - Beta
Classifier: Programming Language :: Python
Classifier: Programming Language :: Python :: 3 :: Only
Classifier: Programming Language :: Python :: 3.10
Classifier: Programming Language :: Python :: 3.11
Classifier: Programming Language :: Python :: 3.12
Classifier: Programming Language :: Python :: 3.13
Classifier: Programming Language :: Python :: 3.14
Classifier: Framework :: Django
Classifier: Framework :: Django :: 5.2
Classifier: Framework :: Django :: 6.0
Classifier: Intended Audience :: Developers
Classifier: Intended Audience :: Science/Research
Classifier: Operating System :: OS Independent
Classifier: Topic :: Scientific/Engineering
Classifier: Topic :: Software Development :: Libraries :: Python Modules
Requires-Python: >=3.10
License-File: LICENSE.txt
Requires-Dist: Django>=5.2
Requires-Dist: pint>=0.16
Dynamic: license-file
